[
	{
		"slug": "notes/how-to-pull-request-fork-github",
		"hits": 127019
	},
	{
		"slug": "notes/shodan-search-queries",
		"hits": 64294
	},
	{
		"slug": "notes/how-to-backup-linux-server",
		"hits": 62595
	},
	{
		"slug": "notes/cloudflare-dns-archive-is-blocked",
		"hits": 48763
	},
	{
		"slug": "notes/github-rename-master",
		"hits": 24888
	},
	{
		"slug": "notes/how-to-shrink-linux-virtual-disk-vmware",
		"hits": 23978
	},
	{
		"slug": "notes/css-waving-hand-emoji",
		"hits": 16857
	},
	{
		"slug": "notes/coronavirus-open-source",
		"hits": 11726
	},
	{
		"slug": "notes/hugo-to-nextjs",
		"hits": 9726
	},
	{
		"slug": "notes/dark-mode",
		"hits": 7980
	},
	{
		"slug": "notes/finding-candidates-subdomain-takeovers",
		"hits": 7806
	},
	{
		"slug": "notes/netlify-analytics-review",
		"hits": 3270
	},
	{
		"slug": "notes/y2k-sandbox",
		"hits": 2870
	},
	{
		"slug": "notes/dropping-dropbox",
		"hits": 2799
	},
	{
		"slug": "notes/security-headers-cloudflare-workers",
		"hits": 2254
	},
	{
		"slug": "notes/github-actions",
		"hits": 2161
	},
	{
		"slug": "notes/my-first-code",
		"hits": 1628
	},
	{
		"slug": "notes/bernie-sanders-bern-app-data",
		"hits": 1514
	},
	{
		"slug": "notes/presidential-candidates-404-pages",
		"hits": 1415
	},
	{
		"slug": "notes/cool-bash-tricks-for-your-terminal-dotfiles",
		"hits": 1032
	},
	{
		"slug": "notes/millenial-with-hillary-clinton",
		"hits": 901
	}
]
