[
	{
		"slug": "notes/how-to-pull-request-fork-github",
		"hits": 122962
	},
	{
		"slug": "notes/how-to-backup-linux-server",
		"hits": 61910
	},
	{
		"slug": "notes/shodan-search-queries",
		"hits": 58281
	},
	{
		"slug": "notes/cloudflare-dns-archive-is-blocked",
		"hits": 44913
	},
	{
		"slug": "notes/github-rename-master",
		"hits": 24317
	},
	{
		"slug": "notes/how-to-shrink-linux-virtual-disk-vmware",
		"hits": 21482
	},
	{
		"slug": "notes/css-waving-hand-emoji",
		"hits": 15576
	},
	{
		"slug": "notes/coronavirus-open-source",
		"hits": 11641
	},
	{
		"slug": "notes/hugo-to-nextjs",
		"hits": 8590
	},
	{
		"slug": "notes/dark-mode",
		"hits": 7660
	},
	{
		"slug": "notes/finding-candidates-subdomain-takeovers",
		"hits": 7572
	},
	{
		"slug": "notes/netlify-analytics-review",
		"hits": 3145
	},
	{
		"slug": "notes/dropping-dropbox",
		"hits": 2651
	},
	{
		"slug": "notes/y2k-sandbox",
		"hits": 2622
	},
	{
		"slug": "notes/security-headers-cloudflare-workers",
		"hits": 2059
	},
	{
		"slug": "notes/github-actions",
		"hits": 1982
	},
	{
		"slug": "notes/my-first-code",
		"hits": 1434
	},
	{
		"slug": "notes/bernie-sanders-bern-app-data",
		"hits": 1424
	},
	{
		"slug": "notes/presidential-candidates-404-pages",
		"hits": 1318
	},
	{
		"slug": "notes/cool-bash-tricks-for-your-terminal-dotfiles",
		"hits": 938
	},
	{
		"slug": "notes/millenial-with-hillary-clinton",
		"hits": 839
	}
]
