[
	{
		"slug": "notes/how-to-pull-request-fork-github",
		"hits": 122930
	},
	{
		"slug": "notes/how-to-backup-linux-server",
		"hits": 61897
	},
	{
		"slug": "notes/shodan-search-queries",
		"hits": 58199
	},
	{
		"slug": "notes/cloudflare-dns-archive-is-blocked",
		"hits": 44771
	},
	{
		"slug": "notes/github-rename-master",
		"hits": 24313
	},
	{
		"slug": "notes/how-to-shrink-linux-virtual-disk-vmware",
		"hits": 21445
	},
	{
		"slug": "notes/css-waving-hand-emoji",
		"hits": 15553
	},
	{
		"slug": "notes/coronavirus-open-source",
		"hits": 11639
	},
	{
		"slug": "notes/hugo-to-nextjs",
		"hits": 8577
	},
	{
		"slug": "notes/dark-mode",
		"hits": 7657
	},
	{
		"slug": "notes/finding-candidates-subdomain-takeovers",
		"hits": 7563
	},
	{
		"slug": "notes/netlify-analytics-review",
		"hits": 3144
	},
	{
		"slug": "notes/dropping-dropbox",
		"hits": 2649
	},
	{
		"slug": "notes/y2k-sandbox",
		"hits": 2619
	},
	{
		"slug": "notes/security-headers-cloudflare-workers",
		"hits": 2056
	},
	{
		"slug": "notes/github-actions",
		"hits": 1978
	},
	{
		"slug": "notes/my-first-code",
		"hits": 1432
	},
	{
		"slug": "notes/bernie-sanders-bern-app-data",
		"hits": 1423
	},
	{
		"slug": "notes/presidential-candidates-404-pages",
		"hits": 1317
	},
	{
		"slug": "notes/cool-bash-tricks-for-your-terminal-dotfiles",
		"hits": 936
	},
	{
		"slug": "notes/millenial-with-hillary-clinton",
		"hits": 838
	}
]
