[
	{
		"slug": "notes/how-to-pull-request-fork-github",
		"hits": 126652
	},
	{
		"slug": "notes/shodan-search-queries",
		"hits": 63482
	},
	{
		"slug": "notes/how-to-backup-linux-server",
		"hits": 62499
	},
	{
		"slug": "notes/cloudflare-dns-archive-is-blocked",
		"hits": 48593
	},
	{
		"slug": "notes/github-rename-master",
		"hits": 24775
	},
	{
		"slug": "notes/how-to-shrink-linux-virtual-disk-vmware",
		"hits": 23629
	},
	{
		"slug": "notes/css-waving-hand-emoji",
		"hits": 16720
	},
	{
		"slug": "notes/coronavirus-open-source",
		"hits": 11719
	},
	{
		"slug": "notes/hugo-to-nextjs",
		"hits": 9586
	},
	{
		"slug": "notes/dark-mode",
		"hits": 7945
	},
	{
		"slug": "notes/finding-candidates-subdomain-takeovers",
		"hits": 7785
	},
	{
		"slug": "notes/netlify-analytics-review",
		"hits": 3258
	},
	{
		"slug": "notes/y2k-sandbox",
		"hits": 2847
	},
	{
		"slug": "notes/dropping-dropbox",
		"hits": 2781
	},
	{
		"slug": "notes/security-headers-cloudflare-workers",
		"hits": 2227
	},
	{
		"slug": "notes/github-actions",
		"hits": 2135
	},
	{
		"slug": "notes/my-first-code",
		"hits": 1607
	},
	{
		"slug": "notes/bernie-sanders-bern-app-data",
		"hits": 1501
	},
	{
		"slug": "notes/presidential-candidates-404-pages",
		"hits": 1398
	},
	{
		"slug": "notes/cool-bash-tricks-for-your-terminal-dotfiles",
		"hits": 1025
	},
	{
		"slug": "notes/millenial-with-hillary-clinton",
		"hits": 891
	}
]
