[
	{
		"slug": "notes/how-to-pull-request-fork-github",
		"hits": 126826
	},
	{
		"slug": "notes/shodan-search-queries",
		"hits": 63800
	},
	{
		"slug": "notes/how-to-backup-linux-server",
		"hits": 62535
	},
	{
		"slug": "notes/cloudflare-dns-archive-is-blocked",
		"hits": 48639
	},
	{
		"slug": "notes/github-rename-master",
		"hits": 24819
	},
	{
		"slug": "notes/how-to-shrink-linux-virtual-disk-vmware",
		"hits": 23796
	},
	{
		"slug": "notes/css-waving-hand-emoji",
		"hits": 16785
	},
	{
		"slug": "notes/coronavirus-open-source",
		"hits": 11720
	},
	{
		"slug": "notes/hugo-to-nextjs",
		"hits": 9658
	},
	{
		"slug": "notes/dark-mode",
		"hits": 7960
	},
	{
		"slug": "notes/finding-candidates-subdomain-takeovers",
		"hits": 7798
	},
	{
		"slug": "notes/netlify-analytics-review",
		"hits": 3262
	},
	{
		"slug": "notes/y2k-sandbox",
		"hits": 2855
	},
	{
		"slug": "notes/dropping-dropbox",
		"hits": 2786
	},
	{
		"slug": "notes/security-headers-cloudflare-workers",
		"hits": 2238
	},
	{
		"slug": "notes/github-actions",
		"hits": 2147
	},
	{
		"slug": "notes/my-first-code",
		"hits": 1617
	},
	{
		"slug": "notes/bernie-sanders-bern-app-data",
		"hits": 1510
	},
	{
		"slug": "notes/presidential-candidates-404-pages",
		"hits": 1406
	},
	{
		"slug": "notes/cool-bash-tricks-for-your-terminal-dotfiles",
		"hits": 1028
	},
	{
		"slug": "notes/millenial-with-hillary-clinton",
		"hits": 896
	}
]
