[
	{
		"slug": "notes/how-to-pull-request-fork-github",
		"hits": 130293
	},
	{
		"slug": "notes/shodan-search-queries",
		"hits": 72162
	},
	{
		"slug": "notes/how-to-backup-linux-server",
		"hits": 64650
	},
	{
		"slug": "notes/cloudflare-dns-archive-is-blocked",
		"hits": 51043
	},
	{
		"slug": "notes/how-to-shrink-linux-virtual-disk-vmware",
		"hits": 26551
	},
	{
		"slug": "notes/github-rename-master",
		"hits": 26096
	},
	{
		"slug": "notes/css-waving-hand-emoji",
		"hits": 18658
	},
	{
		"slug": "notes/coronavirus-open-source",
		"hits": 13063
	},
	{
		"slug": "notes/hugo-to-nextjs",
		"hits": 11601
	},
	{
		"slug": "notes/finding-candidates-subdomain-takeovers",
		"hits": 9268
	},
	{
		"slug": "notes/dark-mode",
		"hits": 9168
	},
	{
		"slug": "notes/netlify-analytics-review",
		"hits": 5535
	},
	{
		"slug": "notes/presidential-candidates-404-pages",
		"hits": 3986
	},
	{
		"slug": "notes/y2k-sandbox",
		"hits": 3730
	},
	{
		"slug": "notes/dropping-dropbox",
		"hits": 3600
	},
	{
		"slug": "notes/my-first-code",
		"hits": 3233
	},
	{
		"slug": "notes/security-headers-cloudflare-workers",
		"hits": 3180
	},
	{
		"slug": "notes/github-actions",
		"hits": 3170
	},
	{
		"slug": "notes/bernie-sanders-bern-app-data",
		"hits": 2433
	},
	{
		"slug": "notes/cool-bash-tricks-for-your-terminal-dotfiles",
		"hits": 1634
	},
	{
		"slug": "notes/millenial-with-hillary-clinton",
		"hits": 1350
	}
]
