[
	{
		"slug": "notes/how-to-pull-request-fork-github",
		"hits": 127749
	},
	{
		"slug": "notes/shodan-search-queries",
		"hits": 66694
	},
	{
		"slug": "notes/how-to-backup-linux-server",
		"hits": 62868
	},
	{
		"slug": "notes/cloudflare-dns-archive-is-blocked",
		"hits": 49296
	},
	{
		"slug": "notes/github-rename-master",
		"hits": 25096
	},
	{
		"slug": "notes/how-to-shrink-linux-virtual-disk-vmware",
		"hits": 24801
	},
	{
		"slug": "notes/css-waving-hand-emoji",
		"hits": 17139
	},
	{
		"slug": "notes/coronavirus-open-source",
		"hits": 11746
	},
	{
		"slug": "notes/hugo-to-nextjs",
		"hits": 10065
	},
	{
		"slug": "notes/dark-mode",
		"hits": 8043
	},
	{
		"slug": "notes/finding-candidates-subdomain-takeovers",
		"hits": 7873
	},
	{
		"slug": "notes/netlify-analytics-review",
		"hits": 3302
	},
	{
		"slug": "notes/y2k-sandbox",
		"hits": 2936
	},
	{
		"slug": "notes/dropping-dropbox",
		"hits": 2839
	},
	{
		"slug": "notes/security-headers-cloudflare-workers",
		"hits": 2359
	},
	{
		"slug": "notes/github-actions",
		"hits": 2249
	},
	{
		"slug": "notes/my-first-code",
		"hits": 1723
	},
	{
		"slug": "notes/bernie-sanders-bern-app-data",
		"hits": 1541
	},
	{
		"slug": "notes/presidential-candidates-404-pages",
		"hits": 1449
	},
	{
		"slug": "notes/cool-bash-tricks-for-your-terminal-dotfiles",
		"hits": 1080
	},
	{
		"slug": "notes/millenial-with-hillary-clinton",
		"hits": 921
	}
]
