[
	{
		"slug": "notes/how-to-pull-request-fork-github",
		"hits": 136642
	},
	{
		"slug": "notes/shodan-search-queries",
		"hits": 87803
	},
	{
		"slug": "notes/how-to-backup-linux-server",
		"hits": 69042
	},
	{
		"slug": "notes/cloudflare-dns-archive-is-blocked",
		"hits": 55265
	},
	{
		"slug": "notes/how-to-shrink-linux-virtual-disk-vmware",
		"hits": 30401
	},
	{
		"slug": "notes/github-rename-master",
		"hits": 28383
	},
	{
		"slug": "notes/css-waving-hand-emoji",
		"hits": 21467
	},
	{
		"slug": "notes/coronavirus-open-source",
		"hits": 17933
	},
	{
		"slug": "notes/hugo-to-nextjs",
		"hits": 14905
	},
	{
		"slug": "notes/finding-candidates-subdomain-takeovers",
		"hits": 12514
	},
	{
		"slug": "notes/dark-mode",
		"hits": 11778
	},
	{
		"slug": "notes/presidential-candidates-404-pages",
		"hits": 8364
	},
	{
		"slug": "notes/netlify-analytics-review",
		"hits": 8151
	},
	{
		"slug": "notes/my-first-code",
		"hits": 7562
	},
	{
		"slug": "notes/security-headers-cloudflare-workers",
		"hits": 6186
	},
	{
		"slug": "notes/dropping-dropbox",
		"hits": 5742
	},
	{
		"slug": "notes/y2k-sandbox",
		"hits": 5557
	},
	{
		"slug": "notes/github-actions",
		"hits": 5286
	},
	{
		"slug": "notes/bernie-sanders-bern-app-data",
		"hits": 4546
	},
	{
		"slug": "notes/cool-bash-tricks-for-your-terminal-dotfiles",
		"hits": 2995
	},
	{
		"slug": "notes/tailwind-hater",
		"hits": 2826
	},
	{
		"slug": "notes/millenial-with-hillary-clinton",
		"hits": 2488
	}
]
