[
	{
		"slug": "notes/how-to-pull-request-fork-github",
		"hits": 127405
	},
	{
		"slug": "notes/shodan-search-queries",
		"hits": 65327
	},
	{
		"slug": "notes/how-to-backup-linux-server",
		"hits": 62736
	},
	{
		"slug": "notes/cloudflare-dns-archive-is-blocked",
		"hits": 49006
	},
	{
		"slug": "notes/github-rename-master",
		"hits": 24985
	},
	{
		"slug": "notes/how-to-shrink-linux-virtual-disk-vmware",
		"hits": 24388
	},
	{
		"slug": "notes/css-waving-hand-emoji",
		"hits": 17007
	},
	{
		"slug": "notes/coronavirus-open-source",
		"hits": 11739
	},
	{
		"slug": "notes/hugo-to-nextjs",
		"hits": 9888
	},
	{
		"slug": "notes/dark-mode",
		"hits": 8020
	},
	{
		"slug": "notes/finding-candidates-subdomain-takeovers",
		"hits": 7846
	},
	{
		"slug": "notes/netlify-analytics-review",
		"hits": 3283
	},
	{
		"slug": "notes/y2k-sandbox",
		"hits": 2906
	},
	{
		"slug": "notes/dropping-dropbox",
		"hits": 2824
	},
	{
		"slug": "notes/security-headers-cloudflare-workers",
		"hits": 2301
	},
	{
		"slug": "notes/github-actions",
		"hits": 2205
	},
	{
		"slug": "notes/my-first-code",
		"hits": 1668
	},
	{
		"slug": "notes/bernie-sanders-bern-app-data",
		"hits": 1525
	},
	{
		"slug": "notes/presidential-candidates-404-pages",
		"hits": 1435
	},
	{
		"slug": "notes/cool-bash-tricks-for-your-terminal-dotfiles",
		"hits": 1060
	},
	{
		"slug": "notes/millenial-with-hillary-clinton",
		"hits": 912
	}
]
