[
	{
		"slug": "notes/how-to-pull-request-fork-github",
		"hits": 121948
	},
	{
		"slug": "notes/how-to-backup-linux-server",
		"hits": 61724
	},
	{
		"slug": "notes/shodan-search-queries",
		"hits": 56822
	},
	{
		"slug": "notes/cloudflare-dns-archive-is-blocked",
		"hits": 42833
	},
	{
		"slug": "notes/github-rename-master",
		"hits": 24149
	},
	{
		"slug": "notes/how-to-shrink-linux-virtual-disk-vmware",
		"hits": 20726
	},
	{
		"slug": "notes/css-waving-hand-emoji",
		"hits": 15113
	},
	{
		"slug": "notes/coronavirus-open-source",
		"hits": 11606
	},
	{
		"slug": "notes/hugo-to-nextjs",
		"hits": 8282
	},
	{
		"slug": "notes/dark-mode",
		"hits": 7567
	},
	{
		"slug": "notes/finding-candidates-subdomain-takeovers",
		"hits": 7487
	},
	{
		"slug": "notes/netlify-analytics-review",
		"hits": 3064
	},
	{
		"slug": "notes/dropping-dropbox",
		"hits": 2586
	},
	{
		"slug": "notes/y2k-sandbox",
		"hits": 2550
	},
	{
		"slug": "notes/security-headers-cloudflare-workers",
		"hits": 1994
	},
	{
		"slug": "notes/github-actions",
		"hits": 1899
	},
	{
		"slug": "notes/my-first-code",
		"hits": 1387
	},
	{
		"slug": "notes/bernie-sanders-bern-app-data",
		"hits": 1381
	},
	{
		"slug": "notes/presidential-candidates-404-pages",
		"hits": 1277
	},
	{
		"slug": "notes/cool-bash-tricks-for-your-terminal-dotfiles",
		"hits": 904
	},
	{
		"slug": "notes/millenial-with-hillary-clinton",
		"hits": 792
	}
]
